mongudb/__init__.py
mongudb/functions.py
mongudb/sql.py
mongudb-0.0.3.dist-info/METADATA
mongudb-0.0.3.dist-info/WHEEL
mongudb-0.0.3.dist-info/top_level.txt
mongudb-0.0.3.dist-info/RECORD
