Metadata-Version: 2.1
Name: mongudb
Version: 0.0.3
Summary: Library to query like SQL
Home-page: https://github.com/Phomint/MongoSQL
Author: Patrick Amaral
Author-email: patrick.dev.atom@gmail.com
License: GPLv3
Keywords: databases,mongodb,query,sql
Platform: UNKNOWN
Classifier: Programming Language :: Python :: 3
Classifier: License :: OSI Approved :: GNU General Public License v3 (GPLv3)
Classifier: Operating System :: OS Independent
Requires-Python: >=3.6
Requires-Dist: pymongo
Requires-Dist: dnspython
